fireflies_sdk/__init__.py
fireflies_sdk/api.py
fireflies_sdk-0.1.0.dist-info/METADATA
fireflies_sdk-0.1.0.dist-info/WHEEL
fireflies_sdk-0.1.0.dist-info/top_level.txt
fireflies_sdk-0.1.0.dist-info/RECORD
